migrations_mcp/__init__.py
migrations_mcp/service.py
mseep_mseep_migrations_mcp-0.1.0.dist-info/METADATA
mseep_mseep_migrations_mcp-0.1.0.dist-info/WHEEL
mseep_mseep_migrations_mcp-0.1.0.dist-info/top_level.txt
mseep_mseep_migrations_mcp-0.1.0.dist-info/RECORD
